etc/jenkins-epo.conf
jenkins_epo/__init__.py
jenkins_epo/bot.py
jenkins_epo/cache.py
jenkins_epo/compat.py
jenkins_epo/github.py
jenkins_epo/jenkins.py
jenkins_epo/main.py
jenkins_epo/procedures.py
jenkins_epo/repository.py
jenkins_epo/rest.py
jenkins_epo/script.py
jenkins_epo/settings.py
jenkins_epo/tasks.py
jenkins_epo/utils.py
jenkins_epo/web.py
jenkins_epo/workers.py
jenkins_epo/extensions/__init__.py
jenkins_epo/extensions/core.py
jenkins_epo/extensions/jenkins.py
jenkins_epo-1.160.data/data/lib/systemd/system/jenkins-epo.service
jenkins_epo-1.160.dist-info/DESCRIPTION.rst
jenkins_epo-1.160.dist-info/METADATA
jenkins_epo-1.160.dist-info/RECORD
jenkins_epo-1.160.dist-info/WHEEL
jenkins_epo-1.160.dist-info/entry_points.txt
jenkins_epo-1.160.dist-info/metadata.json
jenkins_epo-1.160.dist-info/top_level.txt
