Metadata-Version: 2.0
Name: jenkins-epo
Version: 1.160
Summary: Leverage Jenkins features for GitHub repositories.
Home-page: http://jenkins-epo.rtfd.io
Author: Étienne BERSAC <etienne.bersac@people-doc.com>, James Pic <james.pic@people-doc.com>
Author-email: rd@novapost.fr
License: GPL v3 or later
Keywords: jenkins,github,yml
Platform: UNKNOWN
Classifier: Development Status :: 4 - Beta
Classifier: Environment :: Console
Classifier: Intended Audience :: Developers
Classifier: License :: OSI Approved :: MIT License
Classifier: Programming Language :: Python
Requires-Dist: aiohttp (<2.0.0)
Requires-Dist: githubpy
Requires-Dist: jenkins-yml[renderer]
Requires-Dist: jenkinsapi
Requires-Dist: pyyaml
Requires-Dist: tenacity
Provides-Extra: release
Requires-Dist: wheel; extra == 'release'
Provides-Extra: test
Requires-Dist: asynctest; extra == 'test'
Requires-Dist: libfaketime; extra == 'test'
Requires-Dist: pytest; extra == 'test'
Requires-Dist: pytest-asyncio; extra == 'test'
Requires-Dist: pytest-cov; extra == 'test'
Requires-Dist: pytest-logging; extra == 'test'
Requires-Dist: pytest-mock; extra == 'test'
